Config/cordy.ini
CordyMotion/CordyMotion.py
CordyMotion/CordyMotionCaller.py
CordyMotion/__init__.py
CordyMotion/cordy.ini
CordyMotion/cordymotioncaller-0.1.0-py3-none-any.whl
deps/cordymotioncaller.whl
home/ls/Bin/Config/cordy.ini
CordyMotion-0.2.5.dist-info/METADATA
CordyMotion-0.2.5.dist-info/WHEEL
CordyMotion-0.2.5.dist-info/top_level.txt
CordyMotion-0.2.5.dist-info/RECORD
