Metadata-Version: 2.1
Name: CordyMotion
Version: 0.2.5
Summary: A package providing Cordy Motion libs
Home-page: https://github.com/yourusername/CordyMotion
Author: Adam
Author-email: haiyang.sun@cordy.com.cn
Classifier: Programming Language :: Python :: 3
Classifier: License :: OSI Approved :: MIT License
Classifier: Operating System :: OS Independent
Requires-Python: >=3.10
